[{"name":"Tri-phase","price":50,"description":"\t\t","canPurchase":true,"soldOut":false,"category":"light","images":["images/image1.jpg","images/image2.jpg","images/image4.jpg"]},{"name":"Invader","price":65,"description":"","canPurchase":true,"soldOut":false,"category":"light","images":["images/image6.jpg"]},{"name":"Strobe","price":20,"description":"","canPurchase":true,"soldOut":false,"category":"light","images":["images/image7.jpg"]},{"name":"Traffic Light","price":50,"description":"","canPurchase":true,"soldOut":false,"category":"light","images":["images/image8.jpg"]},{"name":"Deluxe Speaker & Lighting Set","price":230,"description":"\t\t","canPurchase":true,"soldOut":false,"category":"package","images":["images/image9.jpg"]},{"name":"Twin Speaker Set 1000RMS","price":170,"description":"\t\t","canPurchase":true,"soldOut":false,"category":"sound","images":["images/image10.jpg"]},{"name":"Speaker Box","price":85,"description":"\t\t","canPurchase":true,"soldOut":false,"category":"sound","images":["images/image11.jpg"]}]